{
  "ops:world-patent-data": {
    "@xmlns": {
      "ops": "http://ops.epo.org",
      "$": "http://www.epo.org/exchange",
      "xlink": "http://www.w3.org/1999/xlink"
    },
    "exchange-documents": {
      "exchange-document": {
        "@system": "ops.epo.org",
        "@family-id": "33563839",
        "@country": "US",
        "@doc-number": "7326708",
        "@kind": "B2",
        "bibliographic-data": {
          "publication-reference": {
            "document-id": [
              {
                "@document-id-type": "docdb",
                "country": {
                  "$": "US"
                },
                "doc-number": {
                  "$": "7326708"
                },
                "kind": {
                  "$": "B2"
                },
                "date": {
                  "$": "20080205"
                }
              },
              {
                "@document-id-type": "epodoc",
                "doc-number": {
                  "$": "US7326708"
                },
                "date": {
                  "$": "20080205"
                }
              }
            ]
          },
          "classifications-ipcr": {
            "classification-ipcr": [
              {
                "@sequence": "1",
                "text": {
                  "$": "A61K  31/   495            A I"
                }
              },
              {
                "@sequence": "2",
                "text": {
                  "$": "A61K  31/   498            A I"
                }
              },
              {
                "@sequence": "3",
                "text": {
                  "$": "A61P   3/    10            A I"
                }
              },
              {
                "@sequence": "4",
                "text": {
                  "$": "C07D 471/    04            A I"
                }
              },
              {
                "@sequence": "5",
                "text": {
                  "$": "C07D 487/    04            A I"
                }
              }
            ]
          },
          "patent-classifications": {
            "patent-classification": [
              {
                "@sequence": "1",
                "classification-scheme": {
                  "@office": "EP",
                  "@scheme": "CPCI"
                },
                "section": {
                  "$": "A"
                },
                "class": {
                  "$": "61"
                },
                "subclass": {
                  "$": "P"
                },
                "main-group": {
                  "$": "3"
                },
                "subgroup": {
                  "$": "00"
                },
                "classification-value": {
                  "$": "I"
                },
                "generating-office": {
                  "$": "EP"
                }
              },
              {
                "@sequence": "2",
                "classification-scheme": {
                  "@office": "EP",
                  "@scheme": "CPCI"
                },
                "section": {
                  "$": "A"
                },
                "class": {
                  "$": "61"
                },
                "subclass": {
                  "$": "P"
                },
                "main-group": {
                  "$": "3"
                },
                "subgroup": {
                  "$": "04"
                },
                "classification-value": {
                  "$": "I"
                },
                "generating-office": {
                  "$": "EP"
                }
              },
              {
                "@sequence": "3",
                "classification-scheme": {
                  "@office": "EP",
                  "@scheme": "CPCI"
                },
                "section": {
                  "$": "A"
                },
                "class": {
                  "$": "61"
                },
                "subclass": {
                  "$": "P"
                },
                "main-group": {
                  "$": "3"
                },
                "subgroup": {
                  "$": "10"
                },
                "classification-value": {
                  "$": "I"
                },
                "generating-office": {
                  "$": "EP"
                }
              },
              {
                "@sequence": "4",
                "classification-scheme": {
                  "@office": "EP",
                  "@scheme": "CPCI"
                },
                "section": {
                  "$": "A"
                },
                "class": {
                  "$": "61"
                },
                "subclass": {
                  "$": "P"
                },
                "main-group": {
                  "$": "9"
                },
                "subgroup": {
                  "$": "12"
                },
                "classification-value": {
                  "$": "I"
                },
                "generating-office": {
                  "$": "EP"
                }
              },
              {
                "@sequence": "5",
                "classification-scheme": {
                  "@office": "EP",
                  "@scheme": "CPCI"
                },
                "section": {
                  "$": "C"
                },
                "class": {
                  "$": "07"
                },
                "subclass": {
                  "$": "D"
                },
                "main-group": {
                  "$": "487"
                },
                "subgroup": {
                  "$": "04"
                },
                "classification-value": {
                  "$": "I"
                },
                "generating-office": {
                  "$": "KR"
                }
              },
              {
                "@sequence": "6",
                "classification-scheme": {
                  "@office": "EP",
                  "@scheme": "CPCI"
                },
                "section": {
                  "$": "C"
                },
                "class": {
                  "$": "07"
                },
                "subclass": {
                  "$": "D"
                },
                "main-group": {
                  "$": "487"
                },
                "subgroup": {
                  "$": "04"
                },
                "classification-value": {
                  "$": "I"
                },
                "generating-office": {
                  "$": "US"
                }
              },
              {
                "@sequence": "7",
                "classification-scheme": {
                  "@office": "EP",
                  "@scheme": "CPCI"
                },
                "section": {
                  "$": "C"
                },
                "class": {
                  "$": "07"
                },
                "subclass": {
                  "$": "D"
                },
                "main-group": {
                  "$": "487"
                },
                "subgroup": {
                  "$": "04"
                },
                "classification-value": {
                  "$": "I"
                },
                "generating-office": {
                  "$": "EP"
                }
              },
              {
                "@sequence": "1",
                "classification-scheme": {
                  "@office": "US",
                  "@scheme": "UC"
                },
                "classification-symbol": {
                  "$": "514/249"
                }
              },
              {
                "@sequence": "2",
                "classification-scheme": {
                  "@office": "US",
                  "@scheme": "UC"
                },
                "classification-symbol": {
                  "$": "544/350"
                }
              }
            ]
          },
          "application-reference": {
            "@doc-id": "53932396",
            "document-id": [
              {
                "@document-id-type": "docdb",
                "country": {
                  "$": "US"
                },
                "doc-number": {
                  "$": "87499204"
                },
                "kind": {
                  "$": "A"
                }
              },
              {
                "@document-id-type": "epodoc",
                "doc-number": {
                  "$": "US20040874992"
                },
                "date": {
                  "$": "20040623"
                }
              },
              {
                "@document-id-type": "original",
                "doc-number": {
                  "$": "10874992"
                }
              }
            ]
          },
          "priority-claims": {
            "priority-claim": [
              {
                "@sequence": "1",
                "@kind": "national",
                "document-id": [
                  {
                    "@document-id-type": "epodoc",
                    "doc-number": {
                      "$": "US20030482161P"
                    },
                    "date": {
                      "$": "20030624"
                    }
                  },
                  {
                    "@document-id-type": "original",
                    "doc-number": {
                      "$": "60482161"
                    }
                  }
                ]
              },
              {
                "@sequence": "2",
                "@kind": "national",
                "document-id": {
                  "@document-id-type": "epodoc",
                  "doc-number": {
                    "$": "US20040874992"
                  },
                  "date": {
                    "$": "20040623"
                  }
                }
              }
            ]
          },
          "parties": {
            "applicants": {
              "applicant": [
                {
                  "@sequence": "1",
                  "@data-format": "epodoc",
                  "applicant-name": {
                    "name": {
                      "$": "MERCK & CO INC [US]"
                    }
                  }
                },
                {
                  "@sequence": "1",
                  "@data-format": "original",
                  "applicant-name": {
                    "name": {
                      "$": "CYPES STEPHEN HOWARD,"
                    }
                  }
                },
                {
                  "@sequence": "2",
                  "@data-format": "original",
                  "applicant-name": {
                    "name": {
                      "$": "CHEN ALEX MINHUA,"
                    }
                  }
                },
                {
                  "@sequence": "3",
                  "@data-format": "original",
                  "applicant-name": {
                    "name": {
                      "$": "FERLITA RUSSELL R,"
                    }
                  }
                },
                {
                  "@sequence": "4",
                  "@data-format": "original",
                  "applicant-name": {
                    "name": {
                      "$": "HANSEN KARL,"
                    }
                  }
                },
                {
                  "@sequence": "5",
                  "@data-format": "original",
                  "applicant-name": {
                    "name": {
                      "$": "LEE IVAN,"
                    }
                  }
                },
                {
                  "@sequence": "6",
                  "@data-format": "original",
                  "applicant-name": {
                    "name": {
                      "$": "VYDRA VICKY K,"
                    }
                  }
                },
                {
                  "@sequence": "7",
                  "@data-format": "original",
                  "applicant-name": {
                    "name": {
                      "$": "WENSLOW ROBERT M,"
                    }
                  }
                },
                {
                  "@sequence": "8",
                  "@data-format": "original",
                  "applicant-name": {
                    "name": {
                      "$": "MERCK & CO., INC"
                    }
                  }
                }
              ]
            },
            "inventors": {
              "inventor": [
                {
                  "@sequence": "1",
                  "@data-format": "epodoc",
                  "inventor-name": {
                    "name": {
                      "$": "CYPES STEPHEN HOWARD [US]"
                    }
                  }
                },
                {
                  "@sequence": "2",
                  "@data-format": "epodoc",
                  "inventor-name": {
                    "name": {
                      "$": "CHEN ALEX MINHUA [US]"
                    }
                  }
                },
                {
                  "@sequence": "3",
                  "@data-format": "epodoc",
                  "inventor-name": {
                    "name": {
                      "$": "FERLITA RUSSELL R [US]"
                    }
                  }
                },
                {
                  "@sequence": "4",
                  "@data-format": "epodoc",
                  "inventor-name": {
                    "name": {
                      "$": "HANSEN KARL [US]"
                    }
                  }
                },
                {
                  "@sequence": "5",
                  "@data-format": "epodoc",
                  "inventor-name": {
                    "name": {
                      "$": "LEE IVAN [US]"
                    }
                  }
                },
                {
                  "@sequence": "6",
                  "@data-format": "epodoc",
                  "inventor-name": {
                    "name": {
                      "$": "VYDRA VICKY K [US]"
                    }
                  }
                },
                {
                  "@sequence": "7",
                  "@data-format": "epodoc",
                  "inventor-name": {
                    "name": {
                      "$": "WENSLOW JR ROBERT M [US]"
                    }
                  }
                },
                {
                  "@sequence": "1",
                  "@data-format": "original",
                  "inventor-name": {
                    "name": {
                      "$": "CYPES STEPHEN HOWARD,"
                    }
                  }
                },
                {
                  "@sequence": "2",
                  "@data-format": "original",
                  "inventor-name": {
                    "name": {
                      "$": "CHEN ALEX MINHUA,"
                    }
                  }
                },
                {
                  "@sequence": "3",
                  "@data-format": "original",
                  "inventor-name": {
                    "name": {
                      "$": "FERLITA RUSSELL R,"
                    }
                  }
                },
                {
                  "@sequence": "4",
                  "@data-format": "original",
                  "inventor-name": {
                    "name": {
                      "$": "HANSEN KARL,"
                    }
                  }
                },
                {
                  "@sequence": "5",
                  "@data-format": "original",
                  "inventor-name": {
                    "name": {
                      "$": "LEE IVAN,"
                    }
                  }
                },
                {
                  "@sequence": "6",
                  "@data-format": "original",
                  "inventor-name": {
                    "name": {
                      "$": "VYDRA VICKY K,"
                    }
                  }
                },
                {
                  "@sequence": "7",
                  "@data-format": "original",
                  "inventor-name": {
                    "name": {
                      "$": "WENSLOW ROBERT M,"
                    }
                  }
                },
                {
                  "@sequence": "8",
                  "@data-format": "original",
                  "inventor-name": {
                    "name": {
                      "$": "WENSLOW, JR. ROBERT M"
                    }
                  }
                }
              ]
            }
          },
          "invention-title": {
            "$": "Phosphoric acid salt of a dipeptidyl peptidase-IV inhibitor",
            "@lang": "en"
          },
          "references-cited": {
            "citation": [
              {
                "@cited-phase": "undefined",
                "@cited-by": "applicant",
                "@sequence": "1",
                "patcit": {
                  "@dnum-type": "publication number",
                  "@num": "1",
                  "document-id": [
                    {
                      "@document-id-type": "epodoc",
                      "doc-number": {
                        "$": "US2003100563"
                      },
                      "date": {
                        "$": "20030529"
                      }
                    },
                    {
                      "@document-id-type": "docdb",
                      "country": {
                        "$": "US"
                      },
                      "doc-number": {
                        "$": "2003100563"
                      },
                      "kind": {
                        "$": "A1"
                      },
                      "date": {
                        "$": "20030529"
                      }
                    }
                  ]
                }
              },
              {
                "@cited-phase": "undefined",
                "@cited-by": "applicant",
                "@sequence": "2",
                "patcit": {
                  "@dnum-type": "publication number",
                  "@num": "2",
                  "document-id": [
                    {
                      "@document-id-type": "epodoc",
                      "doc-number": {
                        "$": "US6699871"
                      },
                      "date": {
                        "$": "20040302"
                      }
                    },
                    {
                      "@document-id-type": "docdb",
                      "country": {
                        "$": "US"
                      },
                      "doc-number": {
                        "$": "6699871"
                      },
                      "kind": {
                        "$": "B2"
                      },
                      "date": {
                        "$": "20040302"
                      }
                    }
                  ]
                }
              },
              {
                "@cited-phase": "undefined",
                "@cited-by": "applicant",
                "@sequence": "3",
                "patcit": {
                  "@dnum-type": "publication number",
                  "@num": "3",
                  "document-id": [
                    {
                      "@document-id-type": "epodoc",
                      "doc-number": {
                        "$": "WO2005072530"
                      },
                      "date": {
                        "$": "20050811"
                      }
                    },
                    {
                      "@document-id-type": "docdb",
                      "country": {
                        "$": "WO"
                      },
                      "doc-number": {
                        "$": "2005072530"
                      },
                      "kind": {
                        "$": "A1"
                      },
                      "date": {
                        "$": "20050811"
                      }
                    }
                  ]
                }
              },
              {
                "@cited-phase": "undefined",
                "@cited-by": "applicant",
                "@sequence": "4",
                "patcit": {
                  "@dnum-type": "publication number",
                  "@num": "4",
                  "document-id": [
                    {
                      "@document-id-type": "epodoc",
                      "doc-number": {
                        "$": "WO2006033848"
                      },
                      "date": {
                        "$": "20060330"
                      }
                    },
                    {
                      "@document-id-type": "docdb",
                      "country": {
                        "$": "WO"
                      },
                      "doc-number": {
                        "$": "2006033848"
                      },
                      "kind": {
                        "$": "A1"
                      },
                      "date": {
                        "$": "20060330"
                      }
                    }
                  ]
                }
              },
              {
                "@cited-phase": "undefined",
                "@cited-by": "applicant",
                "@sequence": "5",
                "nplcit": {
                  "@num": "1",
                  "text": {
                    "$": "- Edmondson, S.D., Drug Data Report, vol. 25, No. 3pp. 245-246 (2003)."
                  }
                }
              },
              {
                "@cited-phase": "undefined",
                "@cited-by": "applicant",
                "@sequence": "6",
                "nplcit": {
                  "@num": "2",
                  "text": {
                    "$": "- Database Prous DDR Online-Database Accession No. 2003: 3561."
                  }
                }
              },
              {
                "@cited-phase": "national-search-report",
                "@cited-by": "examiner",
                "@sequence": "1",
                "patcit": {
                  "@dnum-type": "publication number",
                  "@num": "1",
                  "document-id": [
                    {
                      "@document-id-type": "epodoc",
                      "doc-number": {
                        "$": "US6479692"
                      },
                      "name": {
                        "$": "EKWURIBE NNOCHIRI N [US], et al"
                      },
                      "date": {
                        "$": "20021112"
                      }
                    },
                    {
                      "@document-id-type": "docdb",
                      "country": {
                        "$": "US"
                      },
                      "doc-number": {
                        "$": "6479692"
                      },
                      "kind": {
                        "$": "B1"
                      },
                      "name": {
                        "$": "EKWURIBE NNOCHIRI N [US], et al"
                      },
                      "date": {
                        "$": "20021112"
                      }
                    }
                  ]
                }
              },
              {
                "@cited-phase": "national-search-report",
                "@cited-by": "examiner",
                "@sequence": "2",
                "patcit": {
                  "@dnum-type": "publication number",
                  "@num": "2",
                  "document-id": [
                    {
                      "@document-id-type": "epodoc",
                      "doc-number": {
                        "$": "US2006287528"
                      },
                      "name": {
                        "$": "WENSLOW ROBERT M [US], et al"
                      },
                      "date": {
                        "$": "20061221"
                      }
                    },
                    {
                      "@document-id-type": "docdb",
                      "country": {
                        "$": "US"
                      },
                      "doc-number": {
                        "$": "2006287528"
                      },
                      "kind": {
                        "$": "A1"
                      },
                      "name": {
                        "$": "WENSLOW ROBERT M [US], et al"
                      },
                      "date": {
                        "$": "20061221"
                      }
                    }
                  ]
                }
              },
              {
                "@cited-phase": "national-search-report",
                "@cited-by": "examiner",
                "@sequence": "3",
                "patcit": {
                  "@dnum-type": "publication number",
                  "@num": "3",
                  "document-id": [
                    {
                      "@document-id-type": "epodoc",
                      "doc-number": {
                        "$": "US2007021430"
                      },
                      "name": {
                        "$": "CHEN ALEX M [US], et al"
                      },
                      "date": {
                        "$": "20070125"
                      }
                    },
                    {
                      "@document-id-type": "docdb",
                      "country": {
                        "$": "US"
                      },
                      "doc-number": {
                        "$": "2007021430"
                      },
                      "kind": {
                        "$": "A1"
                      },
                      "name": {
                        "$": "CHEN ALEX M [US], et al"
                      },
                      "date": {
                        "$": "20070125"
                      }
                    }
                  ]
                }
              }
            ]
          }
        },
        "abstract": {
          "@lang": "en",
          "p": {
            "$": "The dihydrogenphosphate salt of 4-oxo-4-[3-(trifluoromethyl)-5,6-dihydro [1,2,4]triazolo[4,3-a]pyrazin-7(8H)-yl]-1-(2,4,5-trifluorophenyl)butan-2-amine is a potent inhibitor of dipeptidyl peptidase-IV and is useful for the prevention and/or treatment of non-insulin dependent diabetes mellitus, also referred to as type 2 diabetes. The invention also relates to a crystalline monohydrate of the dihydrogenphosphate salt as well as a process for its preparation, pharmaceutical compositions containing this novel form and methods of use for the treatment of diabetes, obesity, and high blood pressure."
          }
        }
      }
    }
  }
}